COPYING
MANIFEST.in
README
joy2mouse
setup.py
joy2mouse.egg-info/PKG-INFO
joy2mouse.egg-info/SOURCES.txt
joy2mouse.egg-info/dependency_links.txt
joy2mouse.egg-info/requires.txt
joy2mouse.egg-info/top_level.txt
joy2mouselib/__init__.py
joy2mouselib/__init__.pyc
joy2mouselib/joystick.py
joy2mouselib/joystick.pyc
joy2mouselib/keyboard.py
joy2mouselib/keyboard.pyc
joy2mouselib/keyboard_old.py
joy2mouselib/mouse.py
joy2mouselib/mouse.pyc
joy2mouselib/mousethread.py
joy2mouselib/mousethread.pyc
joy2mouselib/profiles.py
joy2mouselib/profiles.pyc