Metadata-Version: 1.0
Name: joy2mouse
Version: 0.1
Summary: Lets you control your mouse-cursor with your joypad/joystick
Home-page: http://launchpad.net/joy2mouse
Author: Daniel Nögel
Author-email: joy2mouse@post.danielnoegel.de
License: GPLv3
Keywords: joypad joystick mouse
Platform: UNKNOWN
Classifier: Development Status :: 4 - Beta
Classifier: Topic :: Utilities
Classifier: License :: OSI Approved :: GNU General Public License (GPL)
Classifier: Programming Language :: Python
